pytest_dhos/__init__.py
pytest_dhos/flask_batteries_fixtures.py
pytest_dhos/jwt_permissions.py
pytest_dhos-1.0.5.dist-info/entry_points.txt
pytest_dhos-1.0.5.dist-info/LICENSE.md
pytest_dhos-1.0.5.dist-info/WHEEL
pytest_dhos-1.0.5.dist-info/METADATA
pytest_dhos-1.0.5.dist-info/RECORD
